calitp_data_infra/__init__.py
calitp_data_infra/auth.py
calitp_data_infra/storage.py
calitp_data_infra-2025.6.5.dist-info/METADATA
calitp_data_infra-2025.6.5.dist-info/WHEEL
calitp_data_infra-2025.6.5.dist-info/RECORD
